[{"name":"Temperature","value":"6.2","units":"°C"},{"name":"Pressure","value":"1006.5","units":"hPa"},{"name":"Humidity","value":"99.7","units":"%"},{"name":"Rainfall","value":"1.3","units":"mm/hr@10:00 "},{"name":"24hr rain","value":"8.6","units":"mm/24hr"},{"name":"Monthly","value":"112.0/84","units":"mm"},{"name":"Dewpoint","value":"6.1","units":"°C"},{"name":"Greenhouse","value":"6.8","units":"°C"},{"name":"Interior","value":"18.3","units":"°C"},{"name":"Garage","value":"7.6","units":"°C"},{"name":"Soil","value":"9.3","units":"°C"},{"name":"Front Garden","value":"7.9","units":"°C"},{"name":"Wind","value":"15 kts, 44° (NE)","units":""},{"name":"Tide","value":"2.9","units":"metres"},{"name":"Date","value":"2023-11-16T10:00:00+0000","units":""},{"name":"Host","value":"38.0°C / 2220","units":"rpm"},{"name":"Dock Source","value":"STX","units":""}]
