[{"name":"Temperature","value":"12.7","units":"°C"},{"name":"Pressure","value":"996.0","units":"hPa"},{"name":"Humidity","value":"99.9","units":"%"},{"name":"Rainfall","value":"2.3","units":"mm/hr@03:44 "},{"name":"24hr rain","value":"19.0","units":"mm/24hr"},{"name":"Monthly","value":"39.4/56","units":"mm"},{"name":"Dewpoint","value":"12.7","units":"°C"},{"name":"Greenhouse","value":"13.1","units":"°C"},{"name":"Interior","value":"21.0","units":"°C"},{"name":"Garage","value":"14.5","units":"°C"},{"name":"Soil","value":"13.6","units":"°C"},{"name":"Front Garden","value":"15.4","units":"°C"},{"name":"Wind","value":"12 kts, 203° (SW)","units":""},{"name":"Tide","value":"4.2","units":"metres"},{"name":"Date","value":"2024-05-14T03:44:00+0100","units":""},{"name":"Host","value":"38.0°C / 2343","units":"rpm"},{"name":"Dock Source","value":"STX","units":""}]
