[{"name":"Temperature","value":"11.2","units":"°C"},{"name":"Pressure","value":"998.2","units":"hPa"},{"name":"Humidity","value":"80.9","units":"%"},{"name":"Rainfall","value":"0.0","units":"mm/hr"},{"name":"Monthly","value":"29.5/79","units":"mm"},{"name":"Dewpoint","value":"8.0","units":"°C"},{"name":"Greenhouse","value":"11.2","units":"°C"},{"name":"Interior","value":"19.2","units":"°C"},{"name":"Garage","value":"12.1","units":"°C"},{"name":"Soil","value":"11.9","units":"°C"},{"name":"Front Garden","value":"12.1","units":"°C"},{"name":"Wind","value":"15 kts, 97° (E)","units":""},{"name":"Tide","value":"4.4","units":"metres"},{"name":"Date","value":"2023-10-18T04:00:00+0100","units":""},{"name":"Host","value":"37.0°C / 2220","units":"rpm"},{"name":"Dock Source","value":"STX","units":""}]
