[{"name":"Temperature","value":"7.7","units":"°C"},{"name":"Pressure","value":"1007.2","units":"hPa"},{"name":"Humidity","value":"99.9","units":"%"},{"name":"Rainfall","value":"0.8","units":"mm/hr@17:00 "},{"name":"24hr rain","value":"10.9","units":"mm/24hr"},{"name":"Monthly","value":"78.5/84","units":"mm"},{"name":"Dewpoint","value":"7.6","units":"°C"},{"name":"Greenhouse","value":"8.1","units":"°C"},{"name":"Interior","value":"21.7","units":"°C"},{"name":"Garage","value":"7.6","units":"°C"},{"name":"Soil","value":"7.9","units":"°C"},{"name":"Front Garden","value":"7.9","units":"°C"},{"name":"Wind","value":"19 kts, 186° (S)","units":""},{"name":"Tide","value":"1.6","units":"metres"},{"name":"Date","value":"2025-11-22T17:00:00+0000","units":""},{"name":"Host","value":"41.0°C / 2812","units":"rpm"},{"name":"Dock Source","value":"STX","units":""}]
