[{"name":"Temperature","value":"10.6","units":"°C"},{"name":"Pressure","value":"1001.4","units":"hPa"},{"name":"Humidity","value":"97.9","units":"%"},{"name":"Rainfall","value":"0.3","units":"mm/hr@21:50 "},{"name":"24hr rain","value":"1.3","units":"mm/24hr"},{"name":"Monthly","value":"77.5/79","units":"mm"},{"name":"Dewpoint","value":"10.3","units":"°C"},{"name":"Greenhouse","value":"10.9","units":"°C"},{"name":"Interior","value":"23.0","units":"°C"},{"name":"Garage","value":"10.0","units":"°C"},{"name":"Soil","value":"10.9","units":"°C"},{"name":"Front Garden","value":"10.9","units":"°C"},{"name":"Wind","value":"15 kts, 261° (W)","units":""},{"name":"Tide","value":"2.5","units":"metres"},{"name":"Date","value":"2025-10-26T22:14:00+0000","units":""},{"name":"Host","value":"42.0°C / 2812","units":"rpm"},{"name":"Dock Source","value":"STX","units":""}]
