[{"name":"Temperature","value":"14.4","units":"°C"},{"name":"Pressure","value":"997.3","units":"hPa"},{"name":"Humidity","value":"96.0","units":"%"},{"name":"Rainfall","value":"3.0","units":"mm/hr@13:00 "},{"name":"24hr rain","value":"7.1","units":"mm/24hr"},{"name":"Monthly","value":"21.1/79","units":"mm"},{"name":"Dewpoint","value":"13.8","units":"°C"},{"name":"Greenhouse","value":"15.1","units":"°C"},{"name":"Interior","value":"22.2","units":"°C"},{"name":"Garage","value":"14.5","units":"°C"},{"name":"Soil","value":"13.6","units":"°C"},{"name":"Front Garden","value":"15.1","units":"°C"},{"name":"Wind","value":"20 kts, 177° (S)","units":""},{"name":"Tide","value":"4.5","units":"metres"},{"name":"Date","value":"2025-10-19T13:00:00+0100","units":""},{"name":"Host","value":"43.0°C / 2812","units":"rpm"},{"name":"Dock Source","value":"STX","units":""}]
