[{"name":"Temperature","value":"10.4","units":"°C"},{"name":"Pressure","value":"1009.9","units":"hPa"},{"name":"Humidity","value":"97.6","units":"%"},{"name":"Rainfall","value":"0.0","units":"mm/hr"},{"name":"24hr rain","value":"4.1","units":"mm/24hr"},{"name":"Monthly","value":"130.3/84","units":"mm"},{"name":"Dewpoint","value":"10.1","units":"°C"},{"name":"Greenhouse","value":"10.8","units":"°C"},{"name":"Interior","value":"20.1","units":"°C"},{"name":"Garage","value":"10.8","units":"°C"},{"name":"Soil","value":"11.0","units":"°C"},{"name":"Front Garden","value":"11.4","units":"°C"},{"name":"Wind","value":"12 kts, 311° (NW)","units":""},{"name":"Tide","value":"3.1","units":"metres"},{"name":"Date","value":"2023-11-20T19:40:00+0000","units":""},{"name":"Host","value":"39.0°C / 2343","units":"rpm"},{"name":"Dock Source","value":"STX","units":""}]
