[{"name":"Temperature","value":"5.0","units":"°C"},{"name":"Pressure","value":"1015.3","units":"hPa"},{"name":"Humidity","value":"99.9","units":"%"},{"name":"Rainfall","value":"0.3","units":"mm/hr@22:50 "},{"name":"24hr rain","value":"10.7","units":"mm/24hr"},{"name":"Monthly","value":"114.0/84","units":"mm"},{"name":"Dewpoint","value":"5.0","units":"°C"},{"name":"Greenhouse","value":"5.4","units":"°C"},{"name":"Interior","value":"19.5","units":"°C"},{"name":"Garage","value":"7.3","units":"°C"},{"name":"Soil","value":"9.2","units":"°C"},{"name":"Front Garden","value":"7.4","units":"°C"},{"name":"Wind","value":"9 kts, 274° (W)","units":""},{"name":"Tide","value":"3.0","units":"metres"},{"name":"Date","value":"2023-11-16T22:50:00+0000","units":""},{"name":"Host","value":"38.0°C / 2343","units":"rpm"},{"name":"Dock Source","value":"STX","units":""}]
