[{"name":"Temperature","value":"7.1","units":"°C"},{"name":"Pressure","value":"998.2","units":"hPa"},{"name":"Humidity","value":"99.9","units":"%"},{"name":"Rainfall","value":"1.0","units":"mm/hr@02:40 "},{"name":"24hr rain","value":"2.3","units":"mm/24hr"},{"name":"Monthly","value":"76.7/84","units":"mm"},{"name":"Dewpoint","value":"7.1","units":"°C"},{"name":"Greenhouse","value":"7.4","units":"°C"},{"name":"Interior","value":"18.0","units":"°C"},{"name":"Garage","value":"7.4","units":"°C"},{"name":"Soil","value":"9.1","units":"°C"},{"name":"Front Garden","value":"8.3","units":"°C"},{"name":"Wind","value":"12 kts, 153° (SE)","units":""},{"name":"Tide","value":"1.8","units":"metres"},{"name":"Date","value":"2023-11-12T02:40:00+0000","units":""},{"name":"Host","value":"37.0°C / 2109","units":"rpm"},{"name":"Dock Source","value":"STX","units":""}]
