[{"name":"Temperature","value":"-1.5","units":"°C"},{"name":"Pressure","value":"1022.0","units":"hPa"},{"name":"Humidity","value":"94.4","units":"%"},{"name":"Rainfall","value":"0.0","units":"mm/hr"},{"name":"Monthly","value":"67.6/84","units":"mm"},{"name":"Dewpoint","value":"-2.4","units":"°C"},{"name":"Greenhouse","value":"-0.8","units":"°C"},{"name":"Interior","value":"19.1","units":"°C"},{"name":"Garage","value":"0.9","units":"°C"},{"name":"Soil","value":"6.9","units":"°C"},{"name":"Front Garden","value":"0.9","units":"°C"},{"name":"Wind","value":"4 kts, 216° (SW)","units":""},{"name":"Tide","value":"4.3","units":"metres"},{"name":"Date","value":"2025-11-22T01:14:00+0000","units":""},{"name":"Host","value":"39.0°C / 2636","units":"rpm"},{"name":"Dock Source","value":"STX","units":""}]
